mcplette/__init__.py
mcplette-0.0.0.dist-info/METADATA
mcplette-0.0.0.dist-info/WHEEL
mcplette-0.0.0.dist-info/RECORD
