Metadata-Version: 2.4
Name: mcplette
Version: 0.0.0
Summary: ASGI MCP Server
Requires-Python: >=3.10
